README.md
setup.cfg
setup.py
quant_survey.egg-info/PKG-INFO
quant_survey.egg-info/SOURCES.txt
quant_survey.egg-info/dependency_links.txt
quant_survey.egg-info/requires.txt
quant_survey.egg-info/top_level.txt
survey/__init__.py
survey/compound_types.py
survey/constants.py
survey/custom_types.py
survey/attributes/__init__.py
survey/attributes/count_attribute.py
survey/attributes/positive_measure_attribute.py
survey/attributes/single_category_attribute.py
survey/attributes/_abstract/__init__.py
survey/attributes/_abstract/respondent_attribute.py
survey/experiments/__init__.py
survey/experiments/attribute_to_question_experiment.py
survey/experiments/experiment_result.py
survey/experiments/question_to_question_experiment.py
survey/experiments/_abstract/__init__.py
survey/experiments/_abstract/experiment.py
survey/experiments/_abstract/mixins.py
survey/generation/__init__.py
survey/generation/dependency.py
survey/generation/formatting.py
survey/generation/html_file.py
survey/generation/survey_document.py
survey/generation/survey_question.py
survey/generation/survey_section.py
survey/generation/termination.py
survey/generation/mixins/__init__.py
survey/generation/mixins/name_index_mixin.py
survey/groups/__init__.py
survey/groups/attribute_groups/__init__.py
survey/groups/attribute_groups/attribute_group.py
survey/groups/attribute_groups/categorical_attribute_group.py
survey/groups/attribute_groups/count_attribute_group.py
survey/groups/attribute_groups/numerical_attribute_group.py
survey/groups/attribute_groups/positive_measure_attribute_group.py
survey/groups/attribute_groups/single_category_attribute_group.py
survey/groups/question_groups/__init__.py
survey/groups/question_groups/categorical_question_group.py
survey/groups/question_groups/count_question_group.py
survey/groups/question_groups/free_text_question_group.py
survey/groups/question_groups/likert_question_group.py
survey/groups/question_groups/multi_choice_question_group.py
survey/groups/question_groups/numerical_question_group.py
survey/groups/question_groups/positive_measure_question_group.py
survey/groups/question_groups/question_group.py
