Metadata-Version: 1.1
Name: quant-survey
Version: 0.0.6
Summary: Library for quantitative survey analysis.
Home-page: https://github.com/vahndi/quant-survey
Author: Vahndi Minah
Author-email: UNKNOWN
License: MIT
Keywords: quant,survey
Platform: UNKNOWN
Classifier: Development Status :: 3 - Alpha
Classifier: Intended Audience :: Developers
Classifier: License :: OSI Approved :: MIT License
Classifier: Programming Language :: Python :: 3
